lanno/__init__.py
lanno/config.py
lanno/utils.py
lanno/annotators/__init__.py
lanno/annotators/base.py
lanno/annotators/gpt.py
lanno/models/__init__.py
lanno/models/base.py
lanno/models/gpt.py
lanno/templates/texts/classification.en.jinja
lanno/templates/texts/classification.zh_cn.jinja
lanno/templates/texts/data_augmentation.en.jinja
lanno/templates/texts/data_augmentation.zh_cn.jinja
lanno/templates/texts/multilabel_classification.en.jinja
lanno/templates/texts/multilabel_classification.zh_cn.jinja
lanno/templates/texts/ner.en.jinja
lanno/templates/texts/ner.zh_cn.jinja
lanno/templates/texts/relation_extraction.en.jinja
lanno/templates/texts/relation_extraction.zh_cn.jinja
lanno-0.1.6.dist-info/LICENSE
lanno-0.1.6.dist-info/METADATA
lanno-0.1.6.dist-info/WHEEL
lanno-0.1.6.dist-info/top_level.txt
lanno-0.1.6.dist-info/RECORD
